nexus/pylon/__init__.py
nexus/pylon/cli.py
nexus/pylon/client.py
nexus/pylon/configs/__init__.py
nexus/pylon/configs/pylon.yaml
nexus/pylon/consts.py
nexus/pylon/drivers/__init__.py
nexus/pylon/drivers/base.py
nexus/pylon/drivers/browser.py
nexus/pylon/drivers/direct.py
nexus/pylon/drivers/selenium.py
nexus/pylon/exceptions.py
nexus/pylon/matcher.py
nexus/pylon/network_agent.py
nexus/pylon/pdftools/__init__.py
nexus/pylon/pdftools/text_collector.py
nexus/pylon/pdftools/watermarks.py
nexus/pylon/prepared_request.py
nexus/pylon/proto/file_pb2.py
nexus/pylon/proxy_manager.py
nexus/pylon/resolvers/__init__.py
nexus/pylon/resolvers/base.py
nexus/pylon/resolvers/doi_org_request.py
nexus/pylon/resolvers/dor_org_request.py
nexus/pylon/resolvers/elsevier.py
nexus/pylon/resolvers/libgen_doi.py
nexus/pylon/resolvers/libgen_md5.py
nexus/pylon/resolvers/libgen_new.py
nexus/pylon/resolvers/regex.py
nexus/pylon/resolvers/request.py
nexus/pylon/resolvers/scihub.py
nexus/pylon/resolvers/template.py
nexus/pylon/source.py
nexus/pylon/sources/dor_org_request.py
nexus/pylon/sources/researchgate.py
nexus/pylon/sources/source.py
nexus/pylon/sources/specific/acm.py
nexus/pylon/sources/specific/annurev.py
nexus/pylon/sources/specific/asce.py
nexus/pylon/sources/specific/jama.py
nexus/pylon/sources/specific/nature.py
nexus/pylon/sources/specific/psychiatrist.py
nexus/pylon/sources/specific/rgmu.py
nexus/pylon/sources/specific/rsc.py
nexus/pylon/sources/specific/rsmu.py
nexus/pylon/sources/specific/science.py
nexus/pylon/sources/specific/wiley.py
nexus/pylon/test.py
nexus/pylon/validators/__init__.py
nexus/pylon/validators/base.py
nexus/pylon/validators/doi.py
nexus/pylon/validators/md5.py
nexus/pylon/validators/pdf.py
nexus_pylon-1.0.4.dist-info/METADATA
nexus_pylon-1.0.4.dist-info/RECORD
nexus_pylon-1.0.4.dist-info/WHEEL
nexus_pylon-1.0.4.dist-info/entry_points.txt
python/google/protobuf/__init__.py
python/google/protobuf/any_pb2.py
python/google/protobuf/api_pb2.py
python/google/protobuf/compiler/__init__.py
python/google/protobuf/compiler/plugin_pb2.py
python/google/protobuf/descriptor.py
python/google/protobuf/descriptor_database.py
