Metadata-Version: 2.1
Name: nexus-pylon
Version: 1.0.4
Author: The Superpirate
Home-page: https://github.com/nexus-stc/hyperboria/tree/master/nexus/pylon
License: MIT License
Classifier: Programming Language :: Python :: 3.8
Requires-Python: >=3.8
Requires-Dist: aiokit >= 1.0.0
Requires-Dist: aiofiles >= 0.8.0
Requires-Dist: aiohttp >= 3.8.1
Requires-Dist: aiohttp_socks >= 0.7.1
Requires-Dist: certifi >= 2022.6.15.1
Requires-Dist: izihawa_configurator >= 1.0.0
Requires-Dist: fire >= 0.4.0
Requires-Dist: jq >= 1.2.2
Requires-Dist: pypdf2 >= 2.10.0
Requires-Dist: python-socks >= 2.0.3
Requires-Dist: selenium >= 4.4.3
Requires-Dist: tenacity >= 8.0.1
